model_X/__init__.py
model_X/bilstm_architectures.py
model_X/config.py
model_X/dense_architectures.py
model_X/transformers_architectures.py
model_X/transformers_utils.py
model_X/utils.py
model_X-0.1.5.dist-info/METADATA
model_X-0.1.5.dist-info/WHEEL
model_X-0.1.5.dist-info/top_level.txt
model_X-0.1.5.dist-info/RECORD
